README
setup.py
Talaria.egg-info/PKG-INFO
Talaria.egg-info/SOURCES.txt
Talaria.egg-info/dependency_links.txt
Talaria.egg-info/requires.txt
Talaria.egg-info/top_level.txt
talaria/__init__.py
talaria/graph.py
talaria/loader.py
talaria/pages.py
talaria/publisher.py
talaria/quickstart.py
talaria/repo.py
talaria/utils.py