Metadata-Version: 1.0
Name: Talaria
Version: 0.2.0
Summary: Talaria, a geek-friendly content management system
Home-page: http://www.imankulov.name/talaria/
Author: Roman Imankulov
Author-email: roman@netangels.ru
License: GNU GPLv2+
Keywords: talaria cms mercurial hg static_html
Platform: UNKNOWN
Classifier: Development Status :: 4 - Beta
Classifier: Environment :: Console
Classifier: License :: OSI Approved :: GNU General Public License (GPL)
Classifier: Topic :: Internet :: WWW/HTTP :: Site Management
Classifier: Topic :: Software Development :: Documentation
